napari_splinedist/__init__.py
napari_splinedist/_logging.py
napari_splinedist/_sample_data.py
napari_splinedist/_widget.py
napari_splinedist/exceptions.py
napari_splinedist/napari.yaml
napari_splinedist/_tests/__init__.py
napari_splinedist/_tests/test_sample_data.py
napari_splinedist/_tests/test_widget.py
napari_splinedist/config/__init__.py
napari_splinedist/config/appdir.py
napari_splinedist/config/config.py
napari_splinedist/config/napari_splinedist_config.json
napari_splinedist/logo/logo_white_small.svg
napari_splinedist/model/__init__.py
napari_splinedist/model/predict.py
napari_splinedist/sample_data/bbbc038.png
napari_splinedist/sample_data/conic.png
napari_splinedist/utils/__init__.py
napari_splinedist/utils/colormap.py
napari_splinedist/utils/download_file.py
napari_splinedist/widgets/__init__.py
napari_splinedist/widgets/color_picker_push_button.py
napari_splinedist/widgets/image_layer_combo_box.py
napari_splinedist/widgets/model_download_widget.py
napari_splinedist/widgets/progress_widget.py
napari_splinedist/widgets/rotating_logo_widget.py
napari_splinedist-0.3.1.dist-info/LICENSE
napari_splinedist-0.3.1.dist-info/METADATA
napari_splinedist-0.3.1.dist-info/WHEEL
napari_splinedist-0.3.1.dist-info/entry_points.txt
napari_splinedist-0.3.1.dist-info/top_level.txt
napari_splinedist-0.3.1.dist-info/RECORD
