Metadata-Version: 2.1
Name: napari-splinedist
Version: 0.3.1
Summary: A napari SplineDist plugin
Home-page: https://github.com/DerThorsten/napari-splinedist
Author: Dr. Thorsten Beier
Author-email: derthorstebeier@gmail.com
License: MIT
Project-URL: Bug Tracker, https://github.com/DerThorsten/napari-splinedist/issues
Project-URL: Documentation, https://github.com/DerThorsten/napari-splinedist#README.md
Project-URL: Source Code, https://github.com/DerThorsten/napari-splinedist
Project-URL: User Support, https://github.com/DerThorsten/napari-splinedist/issues
Classifier: Development Status :: 2 - Pre-Alpha
Classifier: Framework :: napari
Classifier: Intended Audience :: Developers
Classifier: License :: OSI Approved :: MIT License
Classifier: Operating System :: OS Independent
Classifier: Programming Language :: Python
Classifier: Programming Language :: Python :: 3
Classifier: Programming Language :: Python :: 3 :: Only
Classifier: Programming Language :: Python :: 3.8
Classifier: Programming Language :: Python :: 3.9
Classifier: Programming Language :: Python :: 3.10
Classifier: Topic :: Scientific/Engineering :: Image Processing
Requires-Python: >=3.8
License-File: LICENSE
Requires-Dist: pydantic
Requires-Dist: numpy
Requires-Dist: magicgui
Requires-Dist: qtpy
Requires-Dist: stardist (>=0.8.3)
Requires-Dist: splinedist (>=0.1.2)
Requires-Dist: napari-splineit (>=0.3.0)
Requires-Dist: requests
Requires-Dist: tensorflow
Requires-Dist: opencv-python-headless
Provides-Extra: testing
Requires-Dist: tox ; extra == 'testing'
Requires-Dist: pytest ; extra == 'testing'
Requires-Dist: pytest-cov ; extra == 'testing'
Requires-Dist: pytest-qt ; extra == 'testing'
Requires-Dist: napari ; extra == 'testing'
Requires-Dist: pyqt5 ; extra == 'testing'
